unifai/__init__.py
unifai/client/__init__.py
unifai/client/_base_client.py
unifai/client/_chat_client.py
unifai/client/_document_chunker_client.py
unifai/client/_document_db_client.py
unifai/client/_document_loader_client.py
unifai/client/_embedder_client.py
unifai/client/_function_client.py
unifai/client/_rag_client.py
unifai/client/_reranker_client.py
unifai/client/_tokenizer_client.py
unifai/client/_vector_db_client.py
unifai/components/__init__.py
unifai/components/_component_importer.py
unifai/components/_globals.py
unifai/components/_base_components/__base_component.py
unifai/components/_base_components/__init__.py
unifai/components/_base_components/_base_adapter.py
unifai/components/_base_components/_base_chat.py
unifai/components/_base_components/_base_chat_db.py
unifai/components/_base_components/_base_db.py
unifai/components/_base_components/_base_document_chunker.py
unifai/components/_base_components/_base_document_db.py
unifai/components/_base_components/_base_document_loader.py
unifai/components/_base_components/_base_embedder.py
unifai/components/_base_components/_base_executor.py
unifai/components/_base_components/_base_function.py
unifai/components/_base_components/_base_http_client.py
unifai/components/_base_components/_base_input_parser.py
unifai/components/_base_components/_base_llm.py
unifai/components/_base_components/_base_output_parser.py
unifai/components/_base_components/_base_prompt_template.py
unifai/components/_base_components/_base_ragpipe.py
unifai/components/_base_components/_base_reranker.py
unifai/components/_base_components/_base_retriever.py
unifai/components/_base_components/_base_tokenizer.py
unifai/components/_base_components/_base_tool_caller.py
unifai/components/_base_components/_base_toolkit.py
unifai/components/_base_components/_base_vector_db.py
unifai/components/_base_components/_base_vector_db_collection.py
unifai/components/adapters/__init__.py
unifai/components/adapters/anthropic_adapter.py
unifai-0.0.3.dist-info/licenses/LICENSE
unifai-0.0.3.dist-info/METADATA
unifai-0.0.3.dist-info/WHEEL
unifai-0.0.3.dist-info/top_level.txt
unifai-0.0.3.dist-info/RECORD
