Metadata-Version: 2.4
Name: unifai
Version: 0.0.3
Summary: Unify AI clients into a single interface with enhanced Tool Calling support.
Home-page: https://github.com/LucasFaudman/unifai.git
Author: Lucas Faudman
Author-email: Lucas Faudman <lucasfaudman@gmail.com>
License: MIT License
Project-URL: Homepage, https://github.com/LucasFaudman/unifai.git
Project-URL: Repository, https://github.com/LucasFaudman/unifai.git
Classifier: Development Status :: 3 - Alpha
Classifier: Intended Audience :: Developers
Classifier: License :: OSI Approved :: MIT License
Classifier: Programming Language :: Python :: 3
Classifier: Programming Language :: Python :: 3.10
Classifier: Programming Language :: Python :: 3.11
Classifier: Programming Language :: Python :: 3.12
Classifier: Operating System :: OS Independent
Classifier: Topic :: Software Development :: Libraries
Classifier: Topic :: Software Development :: Libraries :: Python Modules
Requires-Python: >=3.10
License-File: LICENSE
Requires-Dist: pydantic
Provides-Extra: dev
Requires-Dist: pytest; extra == "dev"
Provides-Extra: openai
Requires-Dist: openai; extra == "openai"
Provides-Extra: ollama
Requires-Dist: ollama; extra == "ollama"
Provides-Extra: anthropic
Requires-Dist: anthropic; extra == "anthropic"
Dynamic: author
Dynamic: classifier
Dynamic: home-page
Dynamic: license-file
Dynamic: requires-python
